[{"西元日期":"20220101","星期":"六","是否放假":"2","備註":"開國紀念日"},{"西元日期":"20220102","星期":"日","是否放假":"2","備註":""},{"西元日期":"20220103","星期":"一","是否放假":"0","備註":""},{"西元日期":"20220104","星期":"二","是否放假":"0","備註":""},{"西元日期":"20220105","星期":"三","是否放假":"0","備註":""},{"西元日期":"20220106","星期":"四","是否放假":"0","備註":""},{"西元日期":"20220107","星期":"五","是否放假":"0","備註":""},{"西元日期":"20220108","星期":"六","是否放假":"2","備註":""},{"西元日期":"20220109","星期":"日","是否放假":"2","備註":""},{"西元日期":"20220110","星期":"一","是否放假":"0","備註":""},{"西元日期":"20220111","星期":"二","是否放假":"0","備註":""},{"西元日期":"20220112","星期":"三","是否放假":"0","備註":""},{"西元日期":"20220113","星期":"四","是否放假":"0","備註":""},{"西元日期":"20220114","星期":"五","是否放假":"0","備註":""},{"西元日期":"20220115","星期":"六","是否放假":"2","備註":""},{"西元日期":"20220116","星期":"日","是否放假":"2","備註":""},{"西元日期":"20220117","星期":"一","是否放假":"0","備註":""},{"西元日期":"20220118","星期":"二","是否放假":"0","備註":""},{"西元日期":"20220119","星期":"三","是否放假":"0","備註":""},{"西元日期":"20220120","星期":"四","是否放假":"0","備註":""},{"西元日期":"20220121","星期":"五","是否放假":"0","備註":""},{"西元日期":"20220122","星期":"六","是否放假":"0","備註":"補行上班"},{"西元日期":"20220123","星期":"日","是否放假":"2","備註":""},{"西元日期":"20220124","星期":"一","是否放假":"0","備註":""},{"西元日期":"20220125","星期":"二","是否放假":"0","備註":""},{"西元日期":"20220126","星期":"三","是否放假":"0","備註":""},{"西元日期":"20220127","星期":"四","是否放假":"0","備註":""},{"西元日期":"20220128","星期":"五","是否放假":"0","備註":""},{"西元日期":"20220129","星期":"六","是否放假":"2","備註":""},{"西元日期":"20220130","星期":"日","是否放假":"2","備註":""},{"西元日期":"20220131","星期":"一","是否放假":"2","備註":"農曆除夕"},{"西元日期":"20220201","星期":"二","是否放假":"2","備註":"春節"},{"西元日期":"20220202","星期":"三","是否放假":"2","備註":"春節"},{"西元日期":"20220203","星期":"四","是否放假":"2","備註":"春節"},{"西元日期":"20220204","星期":"五","是否放假":"2","備註":"調整放假"},{"西元日期":"20220205","星期":"六","是否放假":"2","備註":""},{"西元日期":"20220206","星期":"日","是否放假":"2","備註":""},{"西元日期":"20220207","星期":"一","是否放假":"0","備註":""},{"西元日期":"20220208","星期":"二","是否放假":"0","備註":""},{"西元日期":"20220209","星期":"三","是否放假":"0","備註":""},{"西元日期":"20220210","星期":"四","是否放假":"0","備註":""},{"西元日期":"20220211","星期":"五","是否放假":"0","備註":""},{"西元日期":"20220212","星期":"六","是否放假":"2","備註":""},{"西元日期":"20220213","星期":"日","是否放假":"2","備註":""},{"西元日期":"20220214","星期":"一","是否放假":"0","備註":""},{"西元日期":"20220215","星期":"二","是否放假":"0","備註":""},{"西元日期":"20220216","星期":"三","是否放假":"0","備註":""},{"西元日期":"20220217","星期":"四","是否放假":"0","備註":""},{"西元日期":"20220218","星期":"五","是否放假":"0","備註":""},{"西元日期":"20220219","星期":"六","是否放假":"2","備註":""},{"西元日期":"20220220","星期":"日","是否放假":"2","備註":""},{"西元日期":"20220221","星期":"一","是否放假":"0","備註":""},{"西元日期":"20220222","星期":"二","是否放假":"0","備註":""},{"西元日期":"20220223","星期":"三","是否放假":"0","備註":""},{"西元日期":"20220224","星期":"四","是否放假":"0","備註":""},{"西元日期":"20220225","星期":"五","是否放假":"0","備註":""},{"西元日期":"20220226","星期":"六","是否放假":"2","備註":""},{"西元日期":"20220227","星期":"日","是否放假":"2","備註":""},{"西元日期":"20220228","星期":"一","是否放假":"2","備註":"和平紀念日"},{"西元日期":"20220301","星期":"二","是否放假":"0","備註":""},{"西元日期":"20220302","星期":"三","是否放假":"0","備註":""},{"西元日期":"20220303","星期":"四","是否放假":"0","備註":""},{"西元日期":"20220304","星期":"五","是否放假":"0","備註":""},{"西元日期":"20220305","星期":"六","是否放假":"2","備註":""},{"西元日期":"20220306","星期":"日","是否放假":"2","備註":""},{"西元日期":"20220307","星期":"一","是否放假":"0","備註":""},{"西元日期":"20220308","星期":"二","是否放假":"0","備註":""},{"西元日期":"20220309","星期":"三","是否放假":"0","備註":""},{"西元日期":"20220310","星期":"四","是否放假":"0","備註":""},{"西元日期":"20220311","星期":"五","是否放假":"0","備註":""},{"西元日期":"20220312","星期":"六","是否放假":"2","備註":""},{"西元日期":"20220313","星期":"日","是否放假":"2","備註":""},{"西元日期":"20220314","星期":"一","是否放假":"0","備註":""},{"西元日期":"20220315","星期":"二","是否放假":"0","備註":""},{"西元日期":"20220316","星期":"三","是否放假":"0","備註":""},{"西元日期":"20220317","星期":"四","是否放假":"0","備註":""},{"西元日期":"20220318","星期":"五","是否放假":"0","備註":""},{"西元日期":"20220319","星期":"六","是否放假":"2","備註":""},{"西元日期":"20220320","星期":"日","是否放假":"2","備註":""},{"西元日期":"20220321","星期":"一","是否放假":"0","備註":""},{"西元日期":"20220322","星期":"二","是否放假":"0","備註":""},{"西元日期":"20220323","星期":"三","是否放假":"0","備註":""},{"西元日期":"20220324","星期":"四","是否放假":"0","備註":""},{"西元日期":"20220325","星期":"五","是否放假":"0","備註":""},{"西元日期":"20220326","星期":"六","是否放假":"2","備註":""},{"西元日期":"20220327","星期":"日","是否放假":"2","備註":""},{"西元日期":"20220328","星期":"一","是否放假":"0","備註":""},{"西元日期":"20220329","星期":"二","是否放假":"0","備註":""},{"西元日期":"20220330","星期":"三","是否放假":"0","備註":""},{"西元日期":"20220331","星期":"四","是否放假":"0","備註":""},{"西元日期":"20220401","星期":"五","是否放假":"0","備註":""},{"西元日期":"20220402","星期":"六","是否放假":"2","備註":""},{"西元日期":"20220403","星期":"日","是否放假":"2","備註":""},{"西元日期":"20220404","星期":"一","是否放假":"2","備註":"兒童節"},{"西元日期":"20220405","星期":"二","是否放假":"2","備註":"民族掃墓節"},{"西元日期":"20220406","星期":"三","是否放假":"0","備註":""},{"西元日期":"20220407","星期":"四","是否放假":"0","備註":""},{"西元日期":"20220408","星期":"五","是否放假":"0","備註":""},{"西元日期":"20220409","星期":"六","是否放假":"2","備註":""},{"西元日期":"20220410","星期":"日","是否放假":"2","備註":""},{"西元日期":"20220411","星期":"一","是否放假":"0","備註":""},{"西元日期":"20220412","星期":"二","是否放假":"0","備註":""},{"西元日期":"20220413","星期":"三","是否放假":"0","備註":""},{"西元日期":"20220414","星期":"四","是否放假":"0","備註":""},{"西元日期":"20220415","星期":"五","是否放假":"0","備註":""},{"西元日期":"20220416","星期":"六","是否放假":"2","備註":""},{"西元日期":"20220417","星期":"日","是否放假":"2","備註":""},{"西元日期":"20220418","星期":"一","是否放假":"0","備註":""},{"西元日期":"20220419","星期":"二","是否放假":"0","備註":""},{"西元日期":"20220420","星期":"三","是否放假":"0","備註":""},{"西元日期":"20220421","星期":"四","是否放假":"0","備註":""},{"西元日期":"20220422","星期":"五","是否放假":"0","備註":""},{"西元日期":"20220423","星期":"六","是否放假":"2","備註":""},{"西元日期":"20220424","星期":"日","是否放假":"2","備註":""},{"西元日期":"20220425","星期":"一","是否放假":"0","備註":""},{"西元日期":"20220426","星期":"二","是否放假":"0","備註":""},{"西元日期":"20220427","星期":"三","是否放假":"0","備註":""},{"西元日期":"20220428","星期":"四","是否放假":"0","備註":""},{"西元日期":"20220429","星期":"五","是否放假":"0","備註":""},{"西元日期":"20220430","星期":"六","是否放假":"2","備註":""},{"西元日期":"20220501","星期":"日","是否放假":"2","備註":""},{"西元日期":"20220502","星期":"一","是否放假":"0","備註":""},{"西元日期":"20220503","星期":"二","是否放假":"0","備註":""},{"西元日期":"20220504","星期":"三","是否放假":"0","備註":""},{"西元日期":"20220505","星期":"四","是否放假":"0","備註":""},{"西元日期":"20220506","星期":"五","是否放假":"0","備註":""},{"西元日期":"20220507","星期":"六","是否放假":"2","備註":""},{"西元日期":"20220508","星期":"日","是否放假":"2","備註":""},{"西元日期":"20220509","星期":"一","是否放假":"0","備註":""},{"西元日期":"20220510","星期":"二","是否放假":"0","備註":""},{"西元日期":"20220511","星期":"三","是否放假":"0","備註":""},{"西元日期":"20220512","星期":"四","是否放假":"0","備註":""},{"西元日期":"20220513","星期":"五","是否放假":"0","備註":""},{"西元日期":"20220514","星期":"六","是否放假":"2","備註":""},{"西元日期":"20220515","星期":"日","是否放假":"2","備註":""},{"西元日期":"20220516","星期":"一","是否放假":"0","備註":""},{"西元日期":"20220517","星期":"二","是否放假":"0","備註":""},{"西元日期":"20220518","星期":"三","是否放假":"0","備註":""},{"西元日期":"20220519","星期":"四","是否放假":"0","備註":""},{"西元日期":"20220520","星期":"五","是否放假":"0","備註":""},{"西元日期":"20220521","星期":"六","是否放假":"2","備註":""},{"西元日期":"20220522","星期":"日","是否放假":"2","備註":""},{"西元日期":"20220523","星期":"一","是否放假":"0","備註":""},{"西元日期":"20220524","星期":"二","是否放假":"0","備註":""},{"西元日期":"20220525","星期":"三","是否放假":"0","備註":""},{"西元日期":"20220526","星期":"四","是否放假":"0","備註":""},{"西元日期":"20220527","星期":"五","是否放假":"0","備註":""},{"西元日期":"20220528","星期":"六","是否放假":"2","備註":""},{"西元日期":"20220529","星期":"日","是否放假":"2","備註":""},{"西元日期":"20220530","星期":"一","是否放假":"0","備註":""},{"西元日期":"20220531","星期":"二","是否放假":"0","備註":""},{"西元日期":"20220601","星期":"三","是否放假":"0","備註":""},{"西元日期":"20220602","星期":"四","是否放假":"0","備註":""},{"西元日期":"20220603","星期":"五","是否放假":"2","備註":"端午節"},{"西元日期":"20220604","星期":"六","是否放假":"2","備註":""},{"西元日期":"20220605","星期":"日","是否放假":"2","備註":""},{"西元日期":"20220606","星期":"一","是否放假":"0","備註":""},{"西元日期":"20220607","星期":"二","是否放假":"0","備註":""},{"西元日期":"20220608","星期":"三","是否放假":"0","備註":""},{"西元日期":"20220609","星期":"四","是否放假":"0","備註":""},{"西元日期":"20220610","星期":"五","是否放假":"0","備註":""},{"西元日期":"20220611","星期":"六","是否放假":"2","備註":""},{"西元日期":"20220612","星期":"日","是否放假":"2","備註":""},{"西元日期":"20220613","星期":"一","是否放假":"0","備註":""},{"西元日期":"20220614","星期":"二","是否放假":"0","備註":""},{"西元日期":"20220615","星期":"三","是否放假":"0","備註":""},{"西元日期":"20220616","星期":"四","是否放假":"0","備註":""},{"西元日期":"20220617","星期":"五","是否放假":"0","備註":""},{"西元日期":"20220618","星期":"六","是否放假":"2","備註":""},{"西元日期":"20220619","星期":"日","是否放假":"2","備註":""},{"西元日期":"20220620","星期":"一","是否放假":"0","備註":""},{"西元日期":"20220621","星期":"二","是否放假":"0","備註":""},{"西元日期":"20220622","星期":"三","是否放假":"0","備註":""},{"西元日期":"20220623","星期":"四","是否放假":"0","備註":""},{"西元日期":"20220624","星期":"五","是否放假":"0","備註":""},{"西元日期":"20220625","星期":"六","是否放假":"2","備註":""},{"西元日期":"20220626","星期":"日","是否放假":"2","備註":""},{"西元日期":"20220627","星期":"一","是否放假":"0","備註":""},{"西元日期":"20220628","星期":"二","是否放假":"0","備註":""},{"西元日期":"20220629","星期":"三","是否放假":"0","備註":""},{"西元日期":"20220630","星期":"四","是否放假":"0","備註":""},{"西元日期":"20220701","星期":"五","是否放假":"0","備註":""},{"西元日期":"20220702","星期":"六","是否放假":"2","備註":""},{"西元日期":"20220703","星期":"日","是否放假":"2","備註":""},{"西元日期":"20220704","星期":"一","是否放假":"0","備註":""},{"西元日期":"20220705","星期":"二","是否放假":"0","備註":""},{"西元日期":"20220706","星期":"三","是否放假":"0","備註":""},{"西元日期":"20220707","星期":"四","是否放假":"0","備註":""},{"西元日期":"20220708","星期":"五","是否放假":"0","備註":""},{"西元日期":"20220709","星期":"六","是否放假":"2","備註":""},{"西元日期":"20220710","星期":"日","是否放假":"2","備註":""},{"西元日期":"20220711","星期":"一","是否放假":"0","備註":""},{"西元日期":"20220712","星期":"二","是否放假":"0","備註":""},{"西元日期":"20220713","星期":"三","是否放假":"0","備註":""},{"西元日期":"20220714","星期":"四","是否放假":"0","備註":""},{"西元日期":"20220715","星期":"五","是否放假":"0","備註":""},{"西元日期":"20220716","星期":"六","是否放假":"2","備註":""},{"西元日期":"20220717","星期":"日","是否放假":"2","備註":""},{"西元日期":"20220718","星期":"一","是否放假":"0","備註":""},{"西元日期":"20220719","星期":"二","是否放假":"0","備註":""},{"西元日期":"20220720","星期":"三","是否放假":"0","備註":""},{"西元日期":"20220721","星期":"四","是否放假":"0","備註":""},{"西元日期":"20220722","星期":"五","是否放假":"0","備註":""},{"西元日期":"20220723","星期":"六","是否放假":"2","備註":""},{"西元日期":"20220724","星期":"日","是否放假":"2","備註":""},{"西元日期":"20220725","星期":"一","是否放假":"0","備註":""},{"西元日期":"20220726","星期":"二","是否放假":"0","備註":""},{"西元日期":"20220727","星期":"三","是否放假":"0","備註":""},{"西元日期":"20220728","星期":"四","是否放假":"0","備註":""},{"西元日期":"20220729","星期":"五","是否放假":"0","備註":""},{"西元日期":"20220730","星期":"六","是否放假":"2","備註":""},{"西元日期":"20220731","星期":"日","是否放假":"2","備註":""},{"西元日期":"20220801","星期":"一","是否放假":"0","備註":""},{"西元日期":"20220802","星期":"二","是否放假":"0","備註":""},{"西元日期":"20220803","星期":"三","是否放假":"0","備註":""},{"西元日期":"20220804","星期":"四","是否放假":"0","備註":""},{"西元日期":"20220805","星期":"五","是否放假":"0","備註":""},{"西元日期":"20220806","星期":"六","是否放假":"2","備註":""},{"西元日期":"20220807","星期":"日","是否放假":"2","備註":""},{"西元日期":"20220808","星期":"一","是否放假":"0","備註":""},{"西元日期":"20220809","星期":"二","是否放假":"0","備註":""},{"西元日期":"20220810","星期":"三","是否放假":"0","備註":""},{"西元日期":"20220811","星期":"四","是否放假":"0","備註":""},{"西元日期":"20220812","星期":"五","是否放假":"0","備註":""},{"西元日期":"20220813","星期":"六","是否放假":"2","備註":""},{"西元日期":"20220814","星期":"日","是否放假":"2","備註":""},{"西元日期":"20220815","星期":"一","是否放假":"0","備註":""},{"西元日期":"20220816","星期":"二","是否放假":"0","備註":""},{"西元日期":"20220817","星期":"三","是否放假":"0","備註":""},{"西元日期":"20220818","星期":"四","是否放假":"0","備註":""},{"西元日期":"20220819","星期":"五","是否放假":"0","備註":""},{"西元日期":"20220820","星期":"六","是否放假":"2","備註":""},{"西元日期":"20220821","星期":"日","是否放假":"2","備註":""},{"西元日期":"20220822","星期":"一","是否放假":"0","備註":""},{"西元日期":"20220823","星期":"二","是否放假":"0","備註":""},{"西元日期":"20220824","星期":"三","是否放假":"0","備註":""},{"西元日期":"20220825","星期":"四","是否放假":"0","備註":""},{"西元日期":"20220826","星期":"五","是否放假":"0","備註":""},{"西元日期":"20220827","星期":"六","是否放假":"2","備註":""},{"西元日期":"20220828","星期":"日","是否放假":"2","備註":""},{"西元日期":"20220829","星期":"一","是否放假":"0","備註":""},{"西元日期":"20220830","星期":"二","是否放假":"0","備註":""},{"西元日期":"20220831","星期":"三","是否放假":"0","備註":""},{"西元日期":"20220901","星期":"四","是否放假":"0","備註":""},{"西元日期":"20220902","星期":"五","是否放假":"0","備註":""},{"西元日期":"20220903","星期":"六","是否放假":"2","備註":""},{"西元日期":"20220904","星期":"日","是否放假":"2","備註":""},{"西元日期":"20220905","星期":"一","是否放假":"0","備註":""},{"西元日期":"20220906","星期":"二","是否放假":"0","備註":""},{"西元日期":"20220907","星期":"三","是否放假":"0","備註":""},{"西元日期":"20220908","星期":"四","是否放假":"0","備註":""},{"西元日期":"20220909","星期":"五","是否放假":"2","備註":"補假"},{"西元日期":"20220910","星期":"六","是否放假":"2","備註":"中秋節"},{"西元日期":"20220911","星期":"日","是否放假":"2","備註":""},{"西元日期":"20220912","星期":"一","是否放假":"0","備註":""},{"西元日期":"20220913","星期":"二","是否放假":"0","備註":""},{"西元日期":"20220914","星期":"三","是否放假":"0","備註":""},{"西元日期":"20220915","星期":"四","是否放假":"0","備註":""},{"西元日期":"20220916","星期":"五","是否放假":"0","備註":""},{"西元日期":"20220917","星期":"六","是否放假":"2","備註":""},{"西元日期":"20220918","星期":"日","是否放假":"2","備註":""},{"西元日期":"20220919","星期":"一","是否放假":"0","備註":""},{"西元日期":"20220920","星期":"二","是否放假":"0","備註":""},{"西元日期":"20220921","星期":"三","是否放假":"0","備註":""},{"西元日期":"20220922","星期":"四","是否放假":"0","備註":""},{"西元日期":"20220923","星期":"五","是否放假":"0","備註":""},{"西元日期":"20220924","星期":"六","是否放假":"2","備註":""},{"西元日期":"20220925","星期":"日","是否放假":"2","備註":""},{"西元日期":"20220926","星期":"一","是否放假":"0","備註":""},{"西元日期":"20220927","星期":"二","是否放假":"0","備註":""},{"西元日期":"20220928","星期":"三","是否放假":"0","備註":""},{"西元日期":"20220929","星期":"四","是否放假":"0","備註":""},{"西元日期":"20220930","星期":"五","是否放假":"0","備註":""},{"西元日期":"20221001","星期":"六","是否放假":"2","備註":""},{"西元日期":"20221002","星期":"日","是否放假":"2","備註":""},{"西元日期":"20221003","星期":"一","是否放假":"0","備註":""},{"西元日期":"20221004","星期":"二","是否放假":"0","備註":""},{"西元日期":"20221005","星期":"三","是否放假":"0","備註":""},{"西元日期":"20221006","星期":"四","是否放假":"0","備註":""},{"西元日期":"20221007","星期":"五","是否放假":"0","備註":""},{"西元日期":"20221008","星期":"六","是否放假":"2","備註":""},{"西元日期":"20221009","星期":"日","是否放假":"2","備註":""},{"西元日期":"20221010","星期":"一","是否放假":"2","備註":"國慶日"},{"西元日期":"20221011","星期":"二","是否放假":"0","備註":""},{"西元日期":"20221012","星期":"三","是否放假":"0","備註":""},{"西元日期":"20221013","星期":"四","是否放假":"0","備註":""},{"西元日期":"20221014","星期":"五","是否放假":"0","備註":""},{"西元日期":"20221015","星期":"六","是否放假":"2","備註":""},{"西元日期":"20221016","星期":"日","是否放假":"2","備註":""},{"西元日期":"20221017","星期":"一","是否放假":"0","備註":""},{"西元日期":"20221018","星期":"二","是否放假":"0","備註":""},{"西元日期":"20221019","星期":"三","是否放假":"0","備註":""},{"西元日期":"20221020","星期":"四","是否放假":"0","備註":""},{"西元日期":"20221021","星期":"五","是否放假":"0","備註":""},{"西元日期":"20221022","星期":"六","是否放假":"2","備註":""},{"西元日期":"20221023","星期":"日","是否放假":"2","備註":""},{"西元日期":"20221024","星期":"一","是否放假":"0","備註":""},{"西元日期":"20221025","星期":"二","是否放假":"0","備註":""},{"西元日期":"20221026","星期":"三","是否放假":"0","備註":""},{"西元日期":"20221027","星期":"四","是否放假":"0","備註":""},{"西元日期":"20221028","星期":"五","是否放假":"0","備註":""},{"西元日期":"20221029","星期":"六","是否放假":"2","備註":""},{"西元日期":"20221030","星期":"日","是否放假":"2","備註":""},{"西元日期":"20221031","星期":"一","是否放假":"0","備註":""},{"西元日期":"20221101","星期":"二","是否放假":"0","備註":""},{"西元日期":"20221102","星期":"三","是否放假":"0","備註":""},{"西元日期":"20221103","星期":"四","是否放假":"0","備註":""},{"西元日期":"20221104","星期":"五","是否放假":"0","備註":""},{"西元日期":"20221105","星期":"六","是否放假":"2","備註":""},{"西元日期":"20221106","星期":"日","是否放假":"2","備註":""},{"西元日期":"20221107","星期":"一","是否放假":"0","備註":""},{"西元日期":"20221108","星期":"二","是否放假":"0","備註":""},{"西元日期":"20221109","星期":"三","是否放假":"0","備註":""},{"西元日期":"20221110","星期":"四","是否放假":"0","備註":""},{"西元日期":"20221111","星期":"五","是否放假":"0","備註":""},{"西元日期":"20221112","星期":"六","是否放假":"2","備註":""},{"西元日期":"20221113","星期":"日","是否放假":"2","備註":""},{"西元日期":"20221114","星期":"一","是否放假":"0","備註":""},{"西元日期":"20221115","星期":"二","是否放假":"0","備註":""},{"西元日期":"20221116","星期":"三","是否放假":"0","備註":""},{"西元日期":"20221117","星期":"四","是否放假":"0","備註":""},{"西元日期":"20221118","星期":"五","是否放假":"0","備註":""},{"西元日期":"20221119","星期":"六","是否放假":"2","備註":""},{"西元日期":"20221120","星期":"日","是否放假":"2","備註":""},{"西元日期":"20221121","星期":"一","是否放假":"0","備註":""},{"西元日期":"20221122","星期":"二","是否放假":"0","備註":""},{"西元日期":"20221123","星期":"三","是否放假":"0","備註":""},{"西元日期":"20221124","星期":"四","是否放假":"0","備註":""},{"西元日期":"20221125","星期":"五","是否放假":"0","備註":""},{"西元日期":"20221126","星期":"六","是否放假":"2","備註":""},{"西元日期":"20221127","星期":"日","是否放假":"2","備註":""},{"西元日期":"20221128","星期":"一","是否放假":"0","備註":""},{"西元日期":"20221129","星期":"二","是否放假":"0","備註":""},{"西元日期":"20221130","星期":"三","是否放假":"0","備註":""},{"西元日期":"20221201","星期":"四","是否放假":"0","備註":""},{"西元日期":"20221202","星期":"五","是否放假":"0","備註":""},{"西元日期":"20221203","星期":"六","是否放假":"2","備註":""},{"西元日期":"20221204","星期":"日","是否放假":"2","備註":""},{"西元日期":"20221205","星期":"一","是否放假":"0","備註":""},{"西元日期":"20221206","星期":"二","是否放假":"0","備註":""},{"西元日期":"20221207","星期":"三","是否放假":"0","備註":""},{"西元日期":"20221208","星期":"四","是否放假":"0","備註":""},{"西元日期":"20221209","星期":"五","是否放假":"0","備註":""},{"西元日期":"20221210","星期":"六","是否放假":"2","備註":""},{"西元日期":"20221211","星期":"日","是否放假":"2","備註":""},{"西元日期":"20221212","星期":"一","是否放假":"0","備註":""},{"西元日期":"20221213","星期":"二","是否放假":"0","備註":""},{"西元日期":"20221214","星期":"三","是否放假":"0","備註":""},{"西元日期":"20221215","星期":"四","是否放假":"0","備註":""},{"西元日期":"20221216","星期":"五","是否放假":"0","備註":""},{"西元日期":"20221217","星期":"六","是否放假":"2","備註":""},{"西元日期":"20221218","星期":"日","是否放假":"2","備註":""},{"西元日期":"20221219","星期":"一","是否放假":"0","備註":""},{"西元日期":"20221220","星期":"二","是否放假":"0","備註":""},{"西元日期":"20221221","星期":"三","是否放假":"0","備註":""},{"西元日期":"20221222","星期":"四","是否放假":"0","備註":""},{"西元日期":"20221223","星期":"五","是否放假":"0","備註":""},{"西元日期":"20221224","星期":"六","是否放假":"2","備註":""},{"西元日期":"20221225","星期":"日","是否放假":"2","備註":""},{"西元日期":"20221226","星期":"一","是否放假":"0","備註":""},{"西元日期":"20221227","星期":"二","是否放假":"0","備註":""},{"西元日期":"20221228","星期":"三","是否放假":"0","備註":""},{"西元日期":"20221229","星期":"四","是否放假":"0","備註":""},{"西元日期":"20221230","星期":"五","是否放假":"0","備註":""},{"西元日期":"20221231","星期":"六","是否放假":"2","備註":""}]